nano_settings/__init__.py
nano_settings/py.typed
nano_settings/src.py
nano_settings/tests.py
nano_settings-0.1.3.dist-info/licenses/LICENSE
nano_settings-0.1.3.dist-info/METADATA
nano_settings-0.1.3.dist-info/WHEEL
nano_settings-0.1.3.dist-info/top_level.txt
nano_settings-0.1.3.dist-info/RECORD
