Metadata-Version: 2.4
Name: nano-settings
Version: 0.1.3
Summary: Extra small env config system (like pydantic-settings, but simpler)
Author-email: Igor Zyktin <nicord@yandex.ru>
Requires-Python: >=3.10
License-File: LICENSE
Dynamic: license-file
